auth_token/__init__.py
auth_token/backends.py
auth_token/config.py
auth_token/decorators.py
auth_token/enums.py
auth_token/exceptions.py
auth_token/middleware.py
auth_token/models.py
auth_token/signals.py
auth_token/utils.py
auth_token/version.py
auth_token/authorization_request/__init__.py
auth_token/authorization_request/backends.py
auth_token/contrib/__init__.py
auth_token/contrib/admin/views.py
auth_token/contrib/common/__init__.py
auth_token/contrib/common/forms.py
auth_token/contrib/common/views.py
auth_token/contrib/common/auth_security/__init__.py
auth_token/contrib/common/auth_security/validators.py
auth_token/contrib/common/auth_security/views.py
auth_token/contrib/common/default/__init__.py
auth_token/contrib/common/default/views.py
auth_token/contrib/is_core_auth/__init__.py
auth_token/contrib/is_core_auth/forms.py
auth_token/contrib/is_core_auth/resource.py
auth_token/contrib/is_core_auth/views.py
auth_token/contrib/is_core_auth/auth_security/__init__.py
auth_token/contrib/is_core_auth/auth_security/resource.py
auth_token/contrib/is_core_auth/default/__init__.py
auth_token/contrib/is_core_auth/default/resource.py
auth_token/contrib/is_core_auth/tests/__init__.py
auth_token/contrib/is_core_auth/tests/auth_test_cases.py
auth_token/contrib/ms_sso/__init__.py
auth_token/contrib/ms_sso/backends.py
auth_token/contrib/ms_sso/helpers.py
auth_token/contrib/ms_sso/urls.py
auth_token/contrib/ms_sso/views.py
auth_token/contrib/rest_framework_auth/__init__.py
auth_token/contrib/rest_framework_auth/authentication.py
auth_token/contrib/rest_framework_auth/serializers.py
auth_token/contrib/rest_framework_auth/views.py
auth_token/contrib/rest_framework_auth/templates/rest_framework_auth/login.html
auth_token/locale/cs/LC_MESSAGES/django.mo
auth_token/locale/cs/LC_MESSAGES/django.po
auth_token/management/__init__.py
auth_token/management/commands/__init__.py
auth_token/management/commands/clean_authorization_requests.py
skip_django_auth_token-0.5.5.dist-info/licenses/LICENSE
skip_django_auth_token-0.5.5.dist-info/METADATA
skip_django_auth_token-0.5.5.dist-info/WHEEL
skip_django_auth_token-0.5.5.dist-info/top_level.txt
skip_django_auth_token-0.5.5.dist-info/RECORD
